LICENSE.txt
MANIFEST.in
README.md
setup.cfg
setup.py
csrc/rw_init.cpp
csrc/utils.h
csrc/cpu/cpu_utils.cpp
csrc/cpu/cpu_utils.h
csrc/cpu/rw_cpu.cpp
csrc/cpu/rw_cpu.h
csrc/cpu/rw_cpu_edge_list.cpp
csrc/cpu/rw_cpu_edge_list.h
csrc/cpu/rw_cpu_triples.cpp
csrc/cpu/rw_cpu_triples.h
csrc/cpu/windows_cpu.cpp
csrc/cpu/windows_cpu.h
csrc/cuda/rw_cuda.cu
csrc/cuda/rw_cuda.h
csrc/cuda/rw_cuda_edge_list.cu
csrc/cuda/rw_cuda_edge_list.h
csrc/cuda/rw_cuda_triples.cu
csrc/cuda/rw_cuda_triples.h
csrc/cuda/utils.cuh
csrc/cuda/windows_cuda.cu
csrc/cuda/windows_cuda.h
tests/__init__.py
tests/test_model.py
tests/test_rw_triples.py
tests/test_windows.py
triple_walk/__init__.py
triple_walk/model.py
triple_walk/rw.py
triple_walk/utils.py
triple_walk.egg-info/PKG-INFO
triple_walk.egg-info/SOURCES.txt
triple_walk.egg-info/dependency_links.txt
triple_walk.egg-info/requires.txt
triple_walk.egg-info/top_level.txt