Metadata-Version: 2.1
Name: triple-walk
Version: 0.0.4
Summary: A pytorch extension library to perform triple walks on knowledge graphs
Home-page: UNKNOWN
Author: Sachin Gavali
Author-email: saching@udel.edu
License: UNKNOWN
Platform: UNKNOWN
